microwler/__init__.py
microwler/crawler.py
microwler/export.py
microwler/page.py
microwler/scrape.py
microwler/settings.py
microwler/utils.py
microwler/cli/__init__.py
microwler/cli/cmd.py
microwler/cli/template.py
microwler/web/__init__.py
microwler/web/backend.py
microwler/web/frontend/dist/.nojekyll
microwler/web/frontend/dist/200.html
microwler/web/frontend/dist/index.html
microwler/web/frontend/dist/logo.png
microwler/web/frontend/dist/night-mode.svg
microwler/web/frontend/dist/_nuxt/27f1a8b.js
microwler/web/frontend/dist/_nuxt/2a86615.js
microwler/web/frontend/dist/_nuxt/46412c9.js
microwler/web/frontend/dist/_nuxt/82b05ef.js
microwler/web/frontend/dist/_nuxt/8720d2f.js
microwler/web/frontend/dist/_nuxt/LICENSES
microwler/web/frontend/dist/_nuxt/b76e6fc.js
microwler/web/frontend/dist/_nuxt/e8b3fbe.js
microwler/web/frontend/dist/_nuxt/fdb647f.js
microwler/web/frontend/dist/connect/index.html
microwler-0.1.8.dist-info/LICENSE
microwler-0.1.8.dist-info/METADATA
microwler-0.1.8.dist-info/WHEEL
microwler-0.1.8.dist-info/entry_points.txt
microwler-0.1.8.dist-info/top_level.txt
microwler-0.1.8.dist-info/RECORD
