Metadata-Version: 2.1
Name: microwler
Version: 0.1.8
Summary: A micro-framework for asynchronous deep crawls and web scraping written in Python
Home-page: https://innovinati.github.io/microwler/
Author: Maximilian Wolf
Author-email: maximilian.wolf@innovinati.com
License: UNKNOWN
Project-URL: Issues, https://github.com/INNOVINATI/microwler/issues
Project-URL: Source, https://github.com/INNOVINATI/microwler/
Platform: UNKNOWN
Classifier: Development Status :: 4 - Beta
Classifier: Intended Audience :: Developers
Classifier: Framework :: AsyncIO
Classifier: License :: OSI Approved :: MIT License
Classifier: Programming Language :: Python :: 3
Classifier: Programming Language :: Python :: 3.7
Classifier: Programming Language :: Python :: 3.8
Classifier: Programming Language :: Python :: 3 :: Only
Requires-Python: >=3.7, <4
Requires-Dist: aiohttp
Requires-Dist: lxml
Requires-Dist: diskcache
Requires-Dist: prettytable
Requires-Dist: quart
Requires-Dist: random-user-agent
Requires-Dist: html-text
Requires-Dist: completely
Requires-Dist: click
Requires-Dist: parsel
Requires-Dist: chardet
Requires-Dist: quart-cors
Requires-Dist: aiodns
